pdf_manager_gui/__init__.py
pdf_manager_gui/__main__.py
pdf_manager_gui-0.3.0.dist-info/METADATA
pdf_manager_gui-0.3.0.dist-info/WHEEL
pdf_manager_gui-0.3.0.dist-info/entry_points.txt
pdf_manager_gui-0.3.0.dist-info/licenses/LICENSE
pdf_manager_gui-0.3.0.dist-info/RECORD
