Metadata-Version: 2.4
Name: pdf-manager-gui
Version: 0.3.0
Summary: Visually compress and OCR PDF files.
License-Expression: GPL-3.0-or-later
License-File: LICENSE
Author: Ioasjfopas
Author-email: Qurium@protonmail.com
Requires-Python: >=3.12
Classifier: Programming Language :: Python :: 3
Classifier: Operating System :: OS Independent
Requires-Dist: ocrmypdf (>=16.12.0,<17.0.0)
Requires-Dist: pyqt6 (>=6.10.0,<7.0.0)
Project-URL: Homepage, https://github.com/ioasjfopas/pdf-manager
Project-URL: Issues, https://github.com/ioasjfopas/pdf-manager/issues
